paicos/__init__.py
paicos/misc.py
paicos/orientation.py
paicos/paicos_user_settings_template.py
paicos/settings.py
paicos/unit_specifications.py
paicos/units.py
paicos/util.py
paicos/cython/__init__.py
paicos/cython/get_derived_variables.cpython-310-darwin.so
paicos/cython/get_derived_variables.pyx
paicos/cython/get_index_of_region.cpython-310-darwin.so
paicos/cython/get_index_of_region.pyx
paicos/cython/histogram.cpython-310-darwin.so
paicos/cython/histogram.pyx
paicos/cython/openmp_info.cpython-310-darwin.so
paicos/cython/openmp_info.pyx
paicos/cython/ray_tracer.cpython-310-darwin.so
paicos/cython/ray_tracer.pyx
paicos/cython/sph_projectors.cpython-310-darwin.so
paicos/cython/sph_projectors.pyx
paicos/derived_variables/__init__.py
paicos/derived_variables/derived_variables.py
paicos/derived_variables/derived_variables_gas.py
paicos/histograms/__init__.py
paicos/histograms/histogram.py
paicos/histograms/histogram2D.py
paicos/image_creators/__init__.py
paicos/image_creators/gpu_ray_projector.py
paicos/image_creators/gpu_sph_projector.py
paicos/image_creators/image_creator.py
paicos/image_creators/image_creator_actions.py
paicos/image_creators/nested_projector.py
paicos/image_creators/projector.py
paicos/image_creators/ray_projector.py
paicos/image_creators/slicer.py
paicos/image_creators/tree_projector.py
paicos/readers/__init__.py
paicos/readers/arepo_catalog.py
paicos/readers/arepo_snap.py
paicos/readers/generic_snap.py
paicos/readers/paicos_readers.py
paicos/trees/__init__.py
paicos/trees/bvh_cpu.py
paicos/trees/bvh_gpu.py
paicos/trees/bvh_tree.cpython-310-darwin.so
paicos/trees/bvh_tree.pyx
paicos/trees/compare_cython_and_numba_implementations.py
paicos/writers/__init__.py
paicos/writers/arepo_image.py
paicos/writers/paicos_writer.py
paicos-0.1.17.dist-info/LICENSE.txt
paicos-0.1.17.dist-info/METADATA
paicos-0.1.17.dist-info/WHEEL
paicos-0.1.17.dist-info/top_level.txt
paicos-0.1.17.dist-info/RECORD
