Metadata-Version: 2.1
Name: paicos
Version: 0.1.17
Summary: An object-oriented Python package for analysis of (cosmological) simulations performed with Arepo.
Home-page: https://github.com/tberlok/paicos
Author: Thomas Berlok
Author-email: Thomas Berlok <tberlok@gmail.com>
License: BSD 3-clause
Classifier: Programming Language :: Python :: 3.8
Classifier: Programming Language :: Python :: 3.9
Classifier: Programming Language :: Python :: 3.10
Classifier: Programming Language :: Python :: 3.11
Requires-Python: >3.8.0
License-File: LICENSE.txt
Requires-Dist: scipy >=1.7.3
Requires-Dist: numpy
Requires-Dist: matplotlib
Requires-Dist: h5py
Requires-Dist: astropy >=4.3
Requires-Dist: numba
Provides-Extra: dev
Requires-Dist: cython ; extra == 'dev'
Requires-Dist: pytest ; extra == 'dev'
Requires-Dist: pytest-order ; extra == 'dev'
Requires-Dist: flake8 ; extra == 'dev'
Requires-Dist: pylint ; extra == 'dev'
